sqlfmt/__init__.py
sqlfmt/__main__.py
sqlfmt/core.py
sqlfmt/sqlfluff.cfg
sqlfmt-0.0.3.dist-info/METADATA
sqlfmt-0.0.3.dist-info/WHEEL
sqlfmt-0.0.3.dist-info/entry_points.txt
sqlfmt-0.0.3.dist-info/top_level.txt
sqlfmt-0.0.3.dist-info/RECORD
