Metadata-Version: 2.1
Name: sqlfmt
Version: 0.0.3
Summary: An uncompromising SQL query formatter.
Author-email: HH-MWB <h.hong@mail.com>
Project-URL: homepage, https://pypi.org/project/sqlfmt/
Project-URL: repository, https://github.com/HH-MWB/sqlfmt
Classifier: Development Status :: 1 - Planning
Classifier: Programming Language :: Python
Classifier: Programming Language :: Python :: 3.7
Classifier: Programming Language :: Python :: 3.8
Classifier: Programming Language :: Python :: 3.9
Classifier: Programming Language :: Python :: 3.10
Classifier: Programming Language :: Python :: 3.11
Classifier: Environment :: Console
Classifier: Operating System :: OS Independent
Requires-Python: >=3.7
Requires-Dist: sqlfluff (~=2.0)
Requires-Dist: typer (~=0.7)
